TIMESERIESANALYSIS2424/__init__.py
TIMESERIESANALYSIS2424/gui.py
TIMESERIESANALYSIS2424/smoothing.py
TIMESERIESANALYSIS2424/stationarity.py
TIMESERIESANALYSIS2424-0.24.dist-info/METADATA
TIMESERIESANALYSIS2424-0.24.dist-info/WHEEL
TIMESERIESANALYSIS2424-0.24.dist-info/top_level.txt
TIMESERIESANALYSIS2424-0.24.dist-info/RECORD
